{
    "id": "213165",
    "first_name": "Amaya",
    "last_name": "Silber",
    "email": "amaya.silber@macys.com",
    "data": {
        "incentive": "3",
        "auto_approve": true,
        "profilePhoto": "\/api\/canvas\/logo\/379786169-0.9373230445664.jpg",
        "job_title": "Women's Shoe Leader ",
        "local_macys_store": "988",
        "racif_id": "71840749",
        "phone_number": "8052015154",
        "tongal": ""
    },
    "last_login_timestamp": "1525819260",
    "created_timestamp": null,
    "modified_timestamp": "2018-05-04 00:33:21",
    "login_id": "1759121",
    "user_id": "213165",
    "role_id": "2",
    "status": "2",
    "fullName": "Amaya Silber",
    "profile_picture": "\/api\/canvas\/logo\/379786169-0.9373230445664.jpg",
    "titleTextEncoded": "amaya-silber",
    "title": "Amaya Silber",
    "videos_count": "0"
}